LICENSE
README.md
setup.py
pesq/__init__.py
pesq/_pesq.py
pesq/cypesq.pyx
pesq/dsp.c
pesq/dsp.h
pesq/pesq.h
pesq/pesqdsp.c
pesq/pesqio.h
pesq/pesqmain.h
pesq/pesqmod.c
pesq/pesqpar.h
pesq.egg-info/PKG-INFO
pesq.egg-info/SOURCES.txt
pesq.egg-info/dependency_links.txt
pesq.egg-info/top_level.txt