Metadata-Version: 2.1
Name: pesq
Version: 0.0.4
Summary: Python Wrapper for PESQ Score (narrow band and wide band)
Home-page: https://github.com/ludlows/python-pesq
Author: ludlows
License: UNKNOWN
Platform: UNKNOWN
Classifier: Programming Language :: Python
Classifier: License :: OSI Approved :: MIT License
Classifier: Operating System :: OS Independent
